oecddatabuilder/__init__.py
oecddatabuilder/databuilder.py
oecddatabuilder/recipe_loader.py
oecddatabuilder/utils.py
oecddatabuilder-0.1.2.dist-info/LICENSE.txt
oecddatabuilder-0.1.2.dist-info/METADATA
oecddatabuilder-0.1.2.dist-info/WHEEL
oecddatabuilder-0.1.2.dist-info/RECORD
