Metadata-Version: 2.3
Name: oecddatabuilder
Version: 0.1.2
Summary: This is a tool for using OECD API builder and creating multiple time series dataframe for economic analysis purposes
Author: minkeymouse
Author-email: minkey.chang@gmail.com
Requires-Python: >=3.10
Classifier: Programming Language :: Python :: 3
Classifier: Programming Language :: Python :: 3.10
Classifier: Programming Language :: Python :: 3.11
Classifier: Programming Language :: Python :: 3.12
Classifier: Programming Language :: Python :: 3.13
Requires-Dist: lxml (>=5.3.2,<6.0.0)
Requires-Dist: pandas (>=2.2.3,<3.0.0)
Requires-Dist: requests (>=2.32.3,<3.0.0)
Requires-Dist: tqdm (>=4.67.1,<5.0.0)
